{"assignees":[],"author":{"id":"MDQ6VXNlcjExMjY1Mw==","is_bot":false,"login":"mattf","name":"Matthew Farrellee"},"body":"**Is your feature request related to a problem? Please describe.**\r\nwriting code with `import cudf as pd`\r\n\r\n**Describe the solution you'd like**\r\n`cudf.to_datetime(..., format=...)` support matching https://pandas.pydata.org/docs/reference/api/pandas.to_datetime.html and https://docs.python.org/3/library/datetime.html#strftime-and-strptime-format-codes\r\n\r\nrelated: https://github.com/rapidsai/cudf/issues/12419","closed":false,"closedAt":null,"comments":[],"createdAt":"2023-01-10T19:22:58Z","id":"I_kwDOBWUGps5bEcLJ","labels":[{"id":"MDU6TGFiZWw1OTk2MjY1NjE=","name":"feature request","description":"New feature or request","color":"a2eeef"},{"id":"MDU6TGFiZWwxMDEzOTg3MzUy","name":"0 - Backlog","description":"In queue waiting for assignment","color":"d4c5f9"},{"id":"MDU6TGFiZWwxMTM5NzQwNjY2","name":"libcudf","description":"Affects libcudf (C++/CUDA) code.","color":"c5def5"},{"id":"MDU6TGFiZWwxMTM5NzQxMjEz","name":"cuDF (Python)","description":"Affects Python cuDF API.","color":"1d76db"}],"milestone":{"number":5,"title":"Pandas API Alignment and Coverage","description":"","dueOn":null},"number":12523,"projectCards":[{"project":{"name":"Feature Planning"},"column":{"name":"Needs prioritizing"}}],"projectItems":[],"reactionGroups":[],"state":"OPEN","title":"[FEA] cudf.to_datetime support locale-specific formatting (%a, %A, %b, %B, %c, %x, %X, %p)","updatedAt":"2023-06-06T03:15:17Z","url":"https://github.com/rapidsai/cudf/issues/12523"}
